mcp_server_anki/__init__.py
mcp_server_anki/server.py
mcp_server_anki-0.2.0.dist-info/METADATA
mcp_server_anki-0.2.0.dist-info/WHEEL
mcp_server_anki-0.2.0.dist-info/entry_points.txt
mcp_server_anki-0.2.0.dist-info/licenses/LICENSE
mcp_server_anki-0.2.0.dist-info/RECORD
