Metadata-Version: 2.4
Name: mcp-server-anki
Version: 0.2.0
Summary: MCP Server for Anki via AnkiConnect
Project-URL: Homepage, https://github.com/cdpath/mcp-server-anki
Project-URL: Repository, https://github.com/cdpath/mcp-server-anki.git
Project-URL: Issues, https://github.com/cdpath/mcp-server-anki/issues
Author-email: cdpath <cdpath@outlook.com>
License-Expression: MIT
License-File: LICENSE
Keywords: anki,ankiconnect,mcp
Classifier: Development Status :: 3 - Alpha
Classifier: Intended Audience :: Developers
Classifier: License :: OSI Approved :: MIT License
Classifier: Programming Language :: Python :: 3
Classifier: Programming Language :: Python :: 3.12
Requires-Python: >=3.10
Requires-Dist: aiohttp>=3.11.16
Requires-Dist: mcp>=1.6.0
